awsbudget.py
CloudFormationClient/__init__.py
CloudFormationClient/budgets.template.yaml
awsbudget-0.0.7.dist-info/METADATA
awsbudget-0.0.7.dist-info/RECORD
awsbudget-0.0.7.dist-info/WHEEL
awsbudget-0.0.7.dist-info/entry_points.txt
awsbudget-0.0.7.dist-info/top_level.txt
