Metadata-Version: 2.1
Name: awsbudget
Version: 0.0.7
Summary: Tool to manage a single, simple AWS Budget
Home-page: https://github.com/dylburger/aws-budgets-cli
Author: Dylan Sather
Author-email: dylan.sather@gmail.com
License: MIT
Keywords: aws,budget
Platform: UNKNOWN
Classifier: Development Status :: 3 - Alpha
Classifier: Intended Audience :: Developers
Classifier: License :: OSI Approved :: MIT License
Requires-Python: >=3
Requires-Dist: boto3
Requires-Dist: click
Requires-Dist: setuptools
